cping/__init__.py
cping/__main__.py
cping/utils.py
cping/layouts/__init__.py
cping/layouts/legacy.py
cping/layouts/modern.py
cping/layouts/tests/__init__.py
cping/layouts/tests/test___init__.py
cping/layouts/tests/test_legacy.py
cping/layouts/tests/test_modern.py
cping/protocols/__init__.py
cping/protocols/icmp.py
cping/protocols/tcp.py
cping/protocols/tests/__init__.py
cping/protocols/tests/test___init__.py
cping/protocols/tests/test_icmp.py
cping/protocols/tests/test_tcp.py
cping/tests/__init__.py
cping/tests/test___main__.py
cping/tests/test_utils.py
cping-0.1.11.dist-info/LICENSE
cping-0.1.11.dist-info/METADATA
cping-0.1.11.dist-info/WHEEL
cping-0.1.11.dist-info/entry_points.txt
cping-0.1.11.dist-info/top_level.txt
cping-0.1.11.dist-info/RECORD
