Metadata-Version: 2.1
Name: cping
Version: 0.1.11
Summary: Concurrent multi-host ping (ICMP and TCP)
Home-page: https://github.com/hSaria/cPing
Author: hSaria
Author-email: sariahajjar@gmail.com
License: MIT
Platform: UNKNOWN
Classifier: Intended Audience :: System Administrators
Classifier: Intended Audience :: Telecommunications Industry
Classifier: License :: OSI Approved :: MIT License
Classifier: Programming Language :: Python :: 3
Classifier: Topic :: Internet
Classifier: Topic :: System :: Networking :: Monitoring
Classifier: Topic :: Utilities
Requires-Python: >=3.6.0
License-File: LICENSE
Requires-Dist: windows-curses ; sys_platform == "win32"
